currency_exchange/README.md
currency_exchange/__init__.py
currency_exchange/converter.py
currency_exchange/data.py
currency_exchange/exceptions.py
currency_exchange/logger.py
pyxrate-0.2.dist-info/LICENSE
pyxrate-0.2.dist-info/METADATA
pyxrate-0.2.dist-info/WHEEL
pyxrate-0.2.dist-info/RECORD
