Metadata-Version: 2.1
Name: pyxrate
Version: 0.2
Summary: A lightweight Python package for retrieving and using foreign exchange rates and convert currencies
Home-page: https://github.com/zemliany/pyxrate
License: MIT
Author: Maksym Zemlianyi
Author-email: m.zemlianyi@setuniversity.edu.ua
Requires-Python: >=3.11,<4.0
Classifier: License :: OSI Approved :: MIT License
Classifier: Programming Language :: Python :: 3
Classifier: Programming Language :: Python :: 3.11
Classifier: Programming Language :: Python :: 3.12
Classifier: Programming Language :: Python :: 3.13
Requires-Dist: aiohttp (==3.11.8)
Requires-Dist: coverage (>=7.6.8,<8.0.0)
Project-URL: Repository, https://github.com/zemliany/pyxrate
